disnakeapi/__init__.py
disnakeapi/api.py
disnakeapi/bot.py
disnakeapi/cog.py
disnakeapi/parser.py
disnakeapi-1.0.0a0.dist-info/LICENSE
disnakeapi-1.0.0a0.dist-info/METADATA
disnakeapi-1.0.0a0.dist-info/WHEEL
disnakeapi-1.0.0a0.dist-info/RECORD
